{
  "method": "EnableLdapAuthentication",
  "params": {
    "authType": "SearchAndBind",
    "groupSearchBaseDN": "dc=prodtest,dc=solidfire,dc=net",
    "groupSearchType": "ActiveDirectory",
    "searchBindDN": "SFReadOnly@prodtest.solidfire.net",
    "searchBindPassword": "password123",
    "sslCert": "",
    "userSearchBaseDN": "dc=prodtest,dc=solidfire,dc=net",
    "userSearchFilter": "(&(objectClass=person)(sAMAccountName=%USERNAME%))",
    "serverURIs":[
      "ldaps://1.2.3.4",
      "ldap://4.3.2.1"
    ]
  },
  "id": 1
}
